sctt/__init__.py
sctt/__main__.py
sctt/app.py
sctt/app.tcss
sctt/version.py
sctt/fonts/7segment.flf
sctt/fonts/7segment_u2588.flf
sctt/fonts/mono_banner.flf
sctt/fonts/mono_banner_u2588.flf
sctt/fonts/term.flf
sctt/modules/__init__.py
sctt/modules/scramble.py
sctt/modules/simulate.py
sctt/modules/timer.py
sctt/renderables/cube_display.py
sctt/screens/__init__.py
sctt/screens/blocking_screen.py
sctt/screens/input_scramble_screen.py
sctt/widgets/__init__.py
sctt/widgets/cube_net_widget.py
sctt/widgets/my_vertical_scroll.py
sctt/widgets/scramble_widget.py
sctt/widgets/status_widget.py
sctt/widgets/timer_widget.py
sctt-0.2.1.dist-info/METADATA
sctt-0.2.1.dist-info/WHEEL
sctt-0.2.1.dist-info/entry_points.txt
sctt-0.2.1.dist-info/licenses/LICENSE
sctt-0.2.1.dist-info/RECORD
