Metadata-Version: 2.3
Name: sctt
Version: 0.2.1
Summary: SpeedCubeTimer-TUI (sctt)
Project-URL: Homepage, https://github.com/sou-san/sctt
Project-URL: Repository, https://github.com/sou-san/sctt
Project-URL: Issues, https://github.com/sou-san/sctt/issues
Project-URL: Documentation, https://github.com/sou-san/sctt/blob/main/README.md
Author-email: sou-san <sou887867@gmail.com>
License: MIT License
Keywords: cli,scrambler,sctt,speed cube timer,terminal,tool,tui
Requires-Python: >=3.12
Requires-Dist: keyboard>=0.13.5
Requires-Dist: rich>=13.9.4
Requires-Dist: textual-pyfiglet>=0.5.5
Requires-Dist: textual>=0.88.1
